setup.py
Flask_Watson.egg-info/PKG-INFO
Flask_Watson.egg-info/SOURCES.txt
Flask_Watson.egg-info/dependency_links.txt
Flask_Watson.egg-info/requires.txt
Flask_Watson.egg-info/top_level.txt
flask_watson/__init__.py
flask_watson/extension.py
flask_watson.egg-info/PKG-INFO
flask_watson.egg-info/SOURCES.txt
flask_watson.egg-info/dependency_links.txt
flask_watson.egg-info/requires.txt
flask_watson.egg-info/top_level.txt