Metadata-Version: 1.0
Name: Flask-Watson
Version: 0.1.0
Summary: Flask-Watson
Home-page: https://github.com/raicheff/flask-watson
Author: Boris Raicheff
Author-email: b@raicheff.com
License: UNKNOWN
Platform: UNKNOWN
